patroni_notifier/__init__.py
patroni_notifier/click.py
patroni_notifier/config.py
patroni_notifier/core.py
patroni_notifier/mail.py
patroni_notifier/templates/backup.html.j2
patroni_notifier/templates/base.html.j2
patroni_notifier/templates/bootstrap.html.j2
patroni_notifier/templates/event.html.j2
patroni_notifier/templates/sections/consul_state.html.j2
patroni_notifier/templates/sections/haproxy_stats.html.j2
patroni_notifier/templates/sections/timeline_history.html.j2
patroni_notifier/templates/simple.txt
patroni_notifier/templates/style.j2.css
patroni_notifier-0.0.4.dist-info/entry_points.txt
patroni_notifier-0.0.4.dist-info/WHEEL
patroni_notifier-0.0.4.dist-info/METADATA
patroni_notifier-0.0.4.dist-info/RECORD
