Metadata-Version: 2.1
Name: patroni-notifier
Version: 0.0.4
Summary: Patoni notification system using jinja2 templates
Home-page: https://github.com/jaredvacanti/patroni-notifier
License: MIT
Keywords: patroni,patroni-extension,ses,email,patroni-notifier
Author: Jared Vacanti
Author-email: jaredvacanti@gmail.com
Requires-Python: >=3.6,<4.0
Classifier: License :: OSI Approved :: MIT License
Classifier: Programming Language :: Python :: 3
Classifier: Programming Language :: Python :: 3.6
Classifier: Programming Language :: Python :: 3.7
Classifier: Programming Language :: Python :: 3.8
Requires-Dist: boto3 (>=1.10.12,<2.0.0)
Requires-Dist: click (>=7.0,<8.0)
Requires-Dist: haproxy-stats (>=1.5,<2.0)
Requires-Dist: humanize (>=0.5.1,<0.6.0)
Requires-Dist: jinja2 (>=2.10.3,<3.0.0)
Requires-Dist: python-consul (>=1.1.0,<2.0.0)
Requires-Dist: python-dateutil (>=2.8,<3.0)
Requires-Dist: python-magic (>=0.4.15,<0.5.0)
Requires-Dist: pytz (>=2019.3,<2020.0)
Requires-Dist: pyyaml (>=5.1,<6.0)
Requires-Dist: requests (>=2.22.0,<3.0.0)
Project-URL: Repository, https://github.com/jaredvacanti/patroni-notifier
